llm_watsonx.py
llm_watsonx-0.1.1.dist-info/LICENSE
llm_watsonx-0.1.1.dist-info/METADATA
llm_watsonx-0.1.1.dist-info/WHEEL
llm_watsonx-0.1.1.dist-info/entry_points.txt
llm_watsonx-0.1.1.dist-info/top_level.txt
llm_watsonx-0.1.1.dist-info/RECORD
