Metadata-Version: 2.1
Name: llm-watsonx
Version: 0.1.1
Summary: LLM plugin for IBM watsonx models
Author: Robby Horvath
License: Apache-2.0
Project-URL: Homepage, https://github.com/h0rv/llm-watsonx
Project-URL: Changelog, https://github.com/h0rv/llm-watsonx/releases
Project-URL: Issues, https://github.com/h0rv/llm-watsonx/issues
Classifier: License :: OSI Approved :: Apache Software License
Requires-Python: >=3.10
License-File: LICENSE
Requires-Dist: llm
Requires-Dist: ibm-watsonx-ai >=1.0.1
Provides-Extra: test
Requires-Dist: pytest ; extra == 'test'
